<?xml version="1.0" encoding="UTF-8"?>


                <points numVertexes="12">

                    <vertex x="-80" y="400" />

                    <vertex x="-80" y="408" />

                    <vertex x="-72" y="408" />

                    <vertex x="-72" y="424" />

                    <vertex x="-80" y="424" />

                    <vertex x="-80" y="432" />

                    <vertex x="-248" y="432" />

                    <vertex x="-248" y="424" />

                    <vertex x="-264" y="424" />

                    <vertex x="-264" y="408" />

                    <vertex x="-248" y="408" />

                    <vertex x="-248" y="400" />

                </points>




<ptm_ratio>100</ptm_ratio>